mkdocs_nbconvert/.gitignore
mkdocs_nbconvert/__init__.py
mkdocs_nbconvert/_version.py
mkdocs_nbconvert/plugin.py
mkdocs_nbconvert/py.typed
mkdocs_nbconvert-0.5.dist-info/licenses/AUTHORS.md
mkdocs_nbconvert-0.5.dist-info/licenses/LICENSE
mkdocs_nbconvert-0.5.dist-info/METADATA
mkdocs_nbconvert-0.5.dist-info/WHEEL
mkdocs_nbconvert-0.5.dist-info/entry_points.txt
mkdocs_nbconvert-0.5.dist-info/top_level.txt
mkdocs_nbconvert-0.5.dist-info/RECORD
