Metadata-Version: 2.4
Name: mkdocs-nbconvert
Version: 0.5
Summary: A MkDocs plug-in provides a source parser for *.ipynb Jupyter notebook files, base on nbconvert.
Author-email: liu xue yan <liu_xue_yan@foxmail.com>
License: BSD-3-Clause
Project-URL: Homepage, https://tanbro.github.io/mkdocs-nbconvert
Project-URL: Repository, https://github.com/tanbro/mkdocs-nbconvert
Project-URL: Documentation, https://tanbro.github.io/mkdocs-nbconvert
Keywords: mkdocs,mkdocs-plugin,jupyter,notebook,jupyter-notebook,markdown,md,nbconvert
Classifier: Development Status :: 5 - Production/Stable
Classifier: Topic :: Documentation
Classifier: Intended Audience :: Developers
Classifier: Programming Language :: Python
Requires-Python: >=3.8
License-File: LICENSE
License-File: AUTHORS.md
Requires-Dist: mkdocs>=1.6
Requires-Dist: nbconvert>=4.2
Requires-Dist: typing-extensions>=4.5.0; python_version < "3.12"
Dynamic: license-file
